MANIFEST.in
setup.cfg
setup.py
django_html_comments/__init__.py
django_html_comments/models.py
django_html_comments/sanitize.py
django_html_comments/tests.py
django_html_comments/views.py
django_html_comments.egg-info/PKG-INFO
django_html_comments.egg-info/SOURCES.txt
django_html_comments.egg-info/dependency_links.txt
django_html_comments.egg-info/not-zip-safe
django_html_comments.egg-info/top_level.txt
django_html_comments/static/js/commenteditor.js