Metadata-Version: 1.1
Name: django-html-comments
Version: 0.3.1
Summary: Django app that provides views to process limited sanitized html comments and a sample tinymce configuration. Compatible with django_comments and Mezzanines ThreadedComments
Home-page: https://github.com/seanodonnell/django_html_comments
Author: Sean O'Donnell
Author-email: sean@odonnell.nu
License: UNKNOWN
Download-URL: https://github.com/seanodonnell/django_html_comments/archive/master.zip
Keywords: django,tinymce,html,comments,mezzanine
Platform: UNKNOWN
Classifier: Programming Language :: Python
Classifier: Development Status :: 4 - Beta
Classifier: Environment :: Plugins
Classifier: Framework :: Django
Classifier: Intended Audience :: Developers
Classifier: License :: OSI Approved :: GNU Lesser General Public License v2 (LGPLv2)
